LICENSE
fiducialary/__init__.py
fiducialary/cli.py
fiducialary-1.1.0.dist-info/LICENSE
fiducialary-1.1.0.dist-info/WHEEL
fiducialary-1.1.0.dist-info/METADATA
fiducialary-1.1.0.dist-info/RECORD
