Metadata-Version: 2.1
Name: fiducialary
Version: 1.1.0
Summary: Generate unique circular fiducial markers for use in vision systems such as photogrammetry.
Home-page: https://gitlab.com/dodgyville/fiducialary
License: LGPLv3+
Author: Luke Miller
Author-email: dodgyville@gmail.com
Requires-Python: >=3.7,<4.0
Classifier: License :: Other/Proprietary License
Classifier: Programming Language :: Python :: 3
Classifier: Programming Language :: Python :: 3.10
Classifier: Programming Language :: Python :: 3.7
Classifier: Programming Language :: Python :: 3.8
Classifier: Programming Language :: Python :: 3.9
Requires-Dist: pycairo (>=1.21.0,<2.0.0)
Requires-Dist: typer (>=0.4.1,<0.5.0)
Project-URL: Repository, https://gitlab.com/dodgyville/fiducialary
